[
  {
    "id": "qweas1",
    "value": "2023년 4월",
    "label": "2023년 4월"
  },
  {
    "id": "qwasd2",
    "value": "2023년 3월",
    "label": "2023년 3월"
  },
  {
    "id": "qcvxas3",
    "value": "2023년 2월",
    "label": "2023년 2월"
  },
  {
    "id": "qnbms4",
    "value": "2023년 1월",
    "label": "2023년 1월"
  },
  {
    "id": "ghjs5",
    "value": "2022년 12월",
    "label": "2022년 12월"
  },
  {
    "id": "yioias6",
    "value": "2022년 11월",
    "label": "2022년 11월"
  },
  {
    "id": "wreeas7",
    "value": "2022년 10월",
    "label": "2022년 10월"
  },
  {
    "id": "gyuos8",
    "value": "2022년 9월",
    "label": "2022년 9월"
  }
]
